pyexplainer/__init__.py
pyexplainer/css/styles.css
pyexplainer/default_data/activemq-5.0.0.zip
pyexplainer/default_data/activemq-5.1.0.zip
pyexplainer/default_data/dflt_data.pkl
pyexplainer/default_data/explained_instance.pkl
pyexplainer/default_data/sample_model.pkl
pyexplainer/default_data/X_explain.csv
pyexplainer/default_data/X_train.csv
pyexplainer/default_data/y_explain.csv
pyexplainer/default_data/y_train.csv
pyexplainer/dev_info/bullet_chart_info.png
pyexplainer/dev_info/bullet_chart_info.txt
pyexplainer/js/bullet.js
pyexplainer/js/d3.min.js
pyexplainer/pyexplainer_pyexplainer.py
pyexplainer/rf_models/jit_dflt_rf_model.pkl
pyexplainer/rulefit.py
pyexplainer-1.2.0.dist-info/LICENSE.md
pyexplainer-1.2.0.dist-info/WHEEL
pyexplainer-1.2.0.dist-info/METADATA
pyexplainer-1.2.0.dist-info/RECORD
